Workbook

Sheet README
A1: Vía Corta Oaxaca — Freight Reactivation Breakeven Model
A3: Puebla (Sánchez) → Oaxaca City, línea E, ~216.5 route-km. Screening level.
A5: WHAT THIS MODEL DOES
A6: Back-solves the annual tonnage required to break even, then expresses it as loaded
A7: truckloads/day each way so it is directly comparable to observed road traffic.
A8: It does NOT forecast demand.
A10: CELL COLOURS
A11: Yellow = input, enter with a source
A12: Orange = ASSUMPTION with no primary source behind it — the honest label, not a value
A13: Green = calculated, do not overtype
A15: THE TWO NUMBERS THAT CARRY THE ANSWER
A16: 1. Contribution margin per ton-km. Not public at commodity level; ARTF's Anuario was
... A33: Regenerate: python3 analysis/scripts/build_breakeven_model.py

Sheet Inputs
A1: Inputs — single editable block
A2: Every downstream sheet reads from here. Orange = assumption with no primary source.
A3: Parameter | B3: Value | C3: Unit | D3: Source | E3: Notes
A4: CORRIDOR
A5: Route length | B5: 216.5 | C5: km | D5: Prompt.md (to verify) | E5: km E-150+000 to E-367+000. Independent verification outstanding
A6: CAPITAL — cost per route-km by track-condition scenario
A7: Light rehabilitation | C7: MXN million / km | E7: UNESCAP guidance cited in brief: < USD 500,000/route-km. Convert at B26 and cite
A8: Heavy rehabilitation | C8: MXN million / km
A9: Substantial reconstruction | C9: MXN million / km
A10: Mexican precedent (context, NOT a base case) | D10: [PRESS — UNVERIFIED] | E10: Press reports ~18,000 MXN million on Línea Z rehabilitation (~300 km) => order ~60 MXN million/km, roughly an order of magnitude above the UNESCAP figure. ASF primary unreachable (JS app), DOF egress-blocked. Must NOT carry a conclusion.
A11: CAPITAL — structures carried separately, per the brief
A12: Bridges / drainage / slope stabilisation — low | C12: MXN million | E12: Dominant uncertainty. Carried as its own line with its own range, NOT buried in a percentage contingency. No public structure inventory is expected to exist
A13: Bridges / drainage / slope stabilisation — high | C13: MXN million
A14: FINANCE
A15: Asset life | B15: 30 | C15: years | D15: Prompt.md
A16: Cost of capital — case 1 | B16: 0.05 | C16: % / yr | D16: Prompt.md
A17: Cost of capital — case 2 | B17: 0.06 | C17: % / yr | D17: Prompt.md
A18: Cost of capital — case 3 | B18: 0.08 | C18: % / yr | D18: Prompt.md
A19: OPERATING
A20: Fixed O&M (tonnage-independent) | C20: MXN million / yr | E20: Signalling, admin, inspection, right-of-way security
A21: Variable O&M per gross ton-km | C21: MXN / gross ton-km | E21: Track wear. This is what makes O&M depend on the tonnage being solved for
A22: Tare factor (gross / net tonnage) | C22: ratio | E22: Wagon tare + locomotive. Gross ton-km = net tons x (1 + tare) x km
A23: REVENUE
A24: Contribution margin per net ton-km | B24: 0.402 | C24: MXN / net ton-km | D24: artf-2024-anuario-ferroviario | E24: Ferrosur EBIT/ton-km, constant 2024 MXN: $0.93 revenue (Tabla 7-8) x 43.19% operating margin (Tablas 7-3, 7.7). ARTF's cost base ALREADY includes maintenance and D&A, so B21 and B20 must be 0 when using this basis or maintenance is double-counted. Swept 0.402-0.93 on 'Supportable'. See working/margin-derivation.md
A25: CONVENTIONS AND CONVERSION
A26: MXN / USD rate | C26: MXN per USD | E26: State the rate AND its date. Required before any USD benchmark is used
A27: FX rate date | C27: date
A28: Deflation base year (INEGI INPC) | C28: yyyy | E28: All money figures real in this year. Never mix nominal across years
A29: ROAD COMPARISON
A30: Payload per loaded articulated truck | B30: 27.5 | C30: tonnes | D30: [ASSUMPTION] 25–30 t | E30: Bridge from vehicle counts to tonnage. This is an ASSUMPTION — show sensitivity
A31: Empty-running share | B31: 0.4 | C31: fraction | D31: Prompt.md: ~30–50% | E31: Raw truck counts are NOT loaded tonnage
A32: Observed articulated veh/day at corridor terminus | B32: 500 | C32: veh/day, both dirs | D32: sct-2025-datosviales-oaxaca | E32: SR-2 bound: endpoint flow N of Oaxaca City. See working/sr2-evaluation.md
A33: Variable O&M — set 0 on the EBIT margin basis | B33: 0 | C33: MXN / gross ton-km | D33: see note | E33: Guard against double-counting; overrides B21 conceptually

Sheet Capital
A1: Capital cost band
A2: Track condition is unknown since 2003 and cannot be resolved from a desk, so capital is bounded by scenario rather than assumed to a base case.
A4: Scenario | B4: Cost per km (MXN m) | C4: Linework (MXN m) | D4: Structures low (MXN m) | E4: Structures high (MXN m) | F4: TOTAL low (MXN m) | G4: TOTAL high (MXN m)
A5: Light rehabilitation | B5: =Inputs!B7 | C5: =IF(OR(B5="",Inputs!$B$5=""),"",B5*Inputs!$B$5) | D5: =Inputs!$B$12 | E5: =Inputs!$B$13 | F5: =IF(OR(C5="",D5=""),"",C5+D5) | G5: =IF(OR(C5="",E5=""),"",C5+E5)
A6: Heavy rehabilitation | B6: =Inputs!B8 | C6: =IF(OR(B6="",Inputs!$B$5=""),"",B6*Inputs!$B$5) | D6: =Inputs!$B$12 | E6: =Inputs!$B$13 | F6: =IF(OR(C6="",D6=""),"",C6+D6) | G6: =IF(OR(C6="",E6=""),"",C6+E6)
A7: Substantial reconstruction | B7: =Inputs!B9 | C7: =IF(OR(B7="",Inputs!$B$5=""),"",B7*Inputs!$B$5) | D7: =Inputs!$B$12 | E7: =Inputs!$B$13 | F7: =IF(OR(C7="",D7=""),"",C7+D7) | G7: =IF(OR(C7="",E7=""),"",C7+E7)
A9: Structures (bridges, drainage, slope stabilisation) are shown as their own range, not folded into a contingency percentage — they are the dominant uncertainty on this alignment and no public structure inventory is expected.
A10: The Cañada de Cuicatlán sits where Sierra Madre Oriental and Sierra Madre del Sur folding converge; documented rainy-season suspension implies scour and slope exposure at water crossings.

Sheet Breakeven
A1: Breakeven tonnage back-solve
A2: T = (AnnualCapital + FixedOM) / ( L × ( margin − varOM × (1+tare) ) ). Closed form: revenue and variable O&M are both linear in tonnage, so the O&M circularity resolves algebraically rather than by iteration.
A3: If margin − varOM×(1+tare) ≤ 0 the line loses money on every incremental tonne and NO tonnage breaks even. The sheet says so rather than returning a number.
A5: Net contribution per net ton-km after track wear | B5: =IF(OR(Inputs!B24="",Inputs!B21="",Inputs!B22=""),"",Inputs!B24-Inputs!B21*(1+Inputs!B22)) | C5: MXN / net ton-km | D5: =IF(B5="","pending margin + O&M inputs",IF(B5<=0,"NO TONNAGE BREAKS EVEN — track wear exceeds margin","positive contribution"))
A7: Capital scenario | B7: Capital (MXN m) | C7: Cost of capital | D7: Annualised capital (MXN m/yr) | E7: Fixed O&M (MXN m/yr) | F7: BREAKEVEN tonnage (net t/yr) | G7: Loaded truckloads/day each way
A8: Light rehab (low structures) | B8: =Capital!F5 | C8: =Inputs!$B$16 | D8: =IF(OR(B8="",C8="",Inputs!$B$15=""),"",-PMT(C8,Inputs!$B$15,B8)) | E8: =Inputs!$B$20 | F8: =IF(OR(D8="",E8="",$B$5="",$B$5<=0,Inputs!$B$5=""),"",(D8+E8)*1000000/(Inputs!$B$5*$B$5)) | G8: =IF(OR(F8="",Inputs!$B$30="",Inputs!$B$30=0),"",F8/(Inputs!$B$30*365*2))
A9: Light rehab (low structures) | B9: =Capital!F5 | C9: =Inputs!$B$17 | D9: =IF(OR(B9="",C9="",Inputs!$B$15=""),"",-PMT(C9,Inputs!$B$15,B9)) | E9: =Inputs!$B$20 | F9: =IF(OR(D9="",E9="",$B$5="",$B$5<=0,Inputs!$B$5=""),"",(D9+E9)*1000000/(Inputs!$B$5*$B$5)) | G9: =IF(OR(F9="",Inputs!$B$30="",Inputs!$B$30=0),"",F9/(Inputs!$B$30*365*2))
A10: Light rehab (low structures) | B10: =Capital!F5 | C10: =Inputs!$B$18 | D10: =IF(OR(B10="",C10="",Inputs!$B$15=""),"",-PMT(C10,Inputs!$B$15,B10)) | E10: =Inputs!$B$20 | F10: =IF(OR(D10="",E10="",$B$5="",$B$5<=0,Inputs!$B$5=""),"",(D10+E10)*1000000/(Inputs!$B$5*$B$5)) | G10: =IF(OR(F10="",Inputs!$B$30="",Inputs!$B$30=0),"",F10/(Inputs!$B$30*365*2))
A11: Light rehab (high structures) | B11: =Capital!G5 | C11: =Inputs!$B$16 | D11: =IF(OR(B11="",C11="",Inputs!$B$15=""),"",-PMT(C11,Inputs!$B$15,B11)) | E11: =Inputs!$B$20 | F11: =IF(OR(D11="",E11="",$B$5="",$B$5<=0,Inputs!$B$5=""),"",(D11+E11)*1000000/(Inputs!$B$5*$B$5)) | G11: =IF(OR(F11="",Inputs!$B$30="",Inputs!$B$30=0),"",F11/(Inputs!$B$30*365*2))
A12: Light rehab (high structures) | B12: =Capital!G5 | C12: =Inputs!$B$17 | D12: =IF(OR(B12="",C12="",Inputs!$B$15=""),"",-PMT(C12,Inputs!$B$15,B12)) | E12: =Inputs!$B$20 | F12: =IF(OR(D12="",E12="",$B$5="",$B$5<=0,Inputs!$B$5=""),"",(D12+E12)*1000000/(Inputs!$B$5*$B$5)) | G12: =IF(OR(F12="",Inputs!$B$30="",Inputs!$B$30=0),"",F12/(Inputs!$B$30*365*2))
A13: Light rehab (high structures) | B13: =Capital!G5 | C13: =Inputs!$B$18 | D13: =IF(OR(B13="",C13="",Inputs!$B$15=""),"",-PMT(C13,Inputs!$B$15,B13)) | E13: =Inputs!$B$20 | F13: =IF(OR(D13="",E13="",$B$5="",$B$5<=0,Inputs!$B$5=""),"",(D13+E13)*1000000/(Inputs!$B$5*$B$5)) | G13: =IF(OR(F13="",Inputs!$B$30="",Inputs!$B$30=0),"",F13/(Inputs!$B$30*365*2))
A14: Heavy rehab (low structures) | B14: =Capital!F6 | C14: =Inputs!$B$16 | D14: =IF(OR(B14="",C14="",Inputs!$B$15=""),"",-PMT(C14,Inputs!$B$15,B14)) | E14: =Inputs!$B$20 | F14: =IF(OR(D14="",E14="",$B$5="",$B$5<=0,Inputs!$B$5=""),"",(D14+E14)*1000000/(Inputs!$B$5*$B$5)) | G14: =IF(OR(F14="",Inputs!$B$30="",Inputs!$B$30=0),"",F14/(Inputs!$B$30*365*2))
A15: Heavy rehab (low structures) | B15: =Capital!F6 | C15: =Inputs!$B$17 | D15: =IF(OR(B15="",C15="",Inputs!$B$15=""),"",-PMT(C15,Inputs!$B$15,B15)) | E15: =Inputs!$B$20 | F15: =IF(OR(D15="",E15="",$B$5="",$B$5<=0,Inputs!$B$5=""),"",(D15+E15)*1000000/(Inputs!$B$5*$B$5)) | G15: =IF(OR(F15="",Inputs!$B$30="",Inputs!$B$30=0),"",F15/(Inputs!$B$30*365*2))
A16: Heavy rehab (low structures) | B16: =Capital!F6 | C16: =Inputs!$B$18 | D16: =IF(OR(B16="",C16="",Inputs!$B$15=""),"",-PMT(C16,Inputs!$B$15,B16)) | E16: =Inputs!$B$20 | F16: =IF(OR(D16="",E16="",$B$5="",$B$5<=0,Inputs!$B$5=""),"",(D16+E16)*1000000/(Inputs!$B$5*$B$5)) | G16: =IF(OR(F16="",Inputs!$B$30="",Inputs!$B$30=0),"",F16/(Inputs!$B$30*365*2))
A17: Heavy rehab (high structures) | B17: =Capital!G6 | C17: =Inputs!$B$16 | D17: =IF(OR(B17="",C17="",Inputs!$B$15=""),"",-PMT(C17,Inputs!$B$15,B17)) | E17: =Inputs!$B$20 | F17: =IF(OR(D17="",E17="",$B$5="",$B$5<=0,Inputs!$B$5=""),"",(D17+E17)*1000000/(Inputs!$B$5*$B$5)) | G17: =IF(OR(F17="",Inputs!$B$30="",Inputs!$B$30=0),"",F17/(Inputs!$B$30*365*2))
A18: Heavy rehab (high structures) | B18: =Capital!G6 | C18: =Inputs!$B$17 | D18: =IF(OR(B18="",C18="",Inputs!$B$15=""),"",-PMT(C18,Inputs!$B$15,B18)) | E18: =Inputs!$B$20 | F18: =IF(OR(D18="",E18="",$B$5="",$B$5<=0,Inputs!$B$5=""),"",(D18+E18)*1000000/(Inputs!$B$5*$B$5)) | G18: =IF(OR(F18="",Inputs!$B$30="",Inputs!$B$30=0),"",F18/(Inputs!$B$30*365*2))
A19: Heavy rehab (high structures) | B19: =Capital!G6 | C19: =Inputs!$B$18 | D19: =IF(OR(B19="",C19="",Inputs!$B$15=""),"",-PMT(C19,Inputs!$B$15,B19)) | E19: =Inputs!$B$20 | F19: =IF(OR(D19="",E19="",$B$5="",$B$5<=0,Inputs!$B$5=""),"",(D19+E19)*1000000/(Inputs!$B$5*$B$5)) | G19: =IF(OR(F19="",Inputs!$B$30="",Inputs!$B$30=0),"",F19/(Inputs!$B$30*365*2))
A20: Substantial recon (low struct.) | B20: =Capital!F7 | C20: =Inputs!$B$16 | D20: =IF(OR(B20="",C20="",Inputs!$B$15=""),"",-PMT(C20,Inputs!$B$15,B20)) | E20: =Inputs!$B$20 | F20: =IF(OR(D20="",E20="",$B$5="",$B$5<=0,Inputs!$B$5=""),"",(D20+E20)*1000000/(Inputs!$B$5*$B$5)) | G20: =IF(OR(F20="",Inputs!$B$30="",Inputs!$B$30=0),"",F20/(Inputs!$B$30*365*2))
A21: Substantial recon (low struct.) | B21: =Capital!F7 | C21: =Inputs!$B$17 | D21: =IF(OR(B21="",C21="",Inputs!$B$15=""),"",-PMT(C21,Inputs!$B$15,B21)) | E21: =Inputs!$B$20 | F21: =IF(OR(D21="",E21="",$B$5="",$B$5<=0,Inputs!$B$5=""),"",(D21+E21)*1000000/(Inputs!$B$5*$B$5)) | G21: =IF(OR(F21="",Inputs!$B$30="",Inputs!$B$30=0),"",F21/(Inputs!$B$30*365*2))
A22: Substantial recon (low struct.) | B22: =Capital!F7 | C22: =Inputs!$B$18 | D22: =IF(OR(B22="",C22="",Inputs!$B$15=""),"",-PMT(C22,Inputs!$B$15,B22)) | E22: =Inputs!$B$20 | F22: =IF(OR(D22="",E22="",$B$5="",$B$5<=0,Inputs!$B$5=""),"",(D22+E22)*1000000/(Inputs!$B$5*$B$5)) | G22: =IF(OR(F22="",Inputs!$B$30="",Inputs!$B$30=0),"",F22/(Inputs!$B$30*365*2))
A23: Substantial recon (high struct.) | B23: =Capital!G7 | C23: =Inputs!$B$16 | D23: =IF(OR(B23="",C23="",Inputs!$B$15=""),"",-PMT(C23,Inputs!$B$15,B23)) | E23: =Inputs!$B$20 | F23: =IF(OR(D23="",E23="",$B$5="",$B$5<=0,Inputs!$B$5=""),"",(D23+E23)*1000000/(Inputs!$B$5*$B$5)) | G23: =IF(OR(F23="",Inputs!$B$30="",Inputs!$B$30=0),"",F23/(Inputs!$B$30*365*2))
A24: Substantial recon (high struct.) | B24: =Capital!G7 | C24: =Inputs!$B$17 | D24: =IF(OR(B24="",C24="",Inputs!$B$15=""),"",-PMT(C24,Inputs!$B$15,B24)) | E24: =Inputs!$B$20 | F24: =IF(OR(D24="",E24="",$B$5="",$B$5<=0,Inputs!$B$5=""),"",(D24+E24)*1000000/(Inputs!$B$5*$B$5)) | G24: =IF(OR(F24="",Inputs!$B$30="",Inputs!$B$30=0),"",F24/(Inputs!$B$30*365*2))
A25: Substantial recon (high struct.) | B25: =Capital!G7 | C25: =Inputs!$B$18 | D25: =IF(OR(B25="",C25="",Inputs!$B$15=""),"",-PMT(C25,Inputs!$B$15,B25)) | E25: =Inputs!$B$20 | F25: =IF(OR(D25="",E25="",$B$5="",$B$5<=0,Inputs!$B$5=""),"",(D25+E25)*1000000/(Inputs!$B$5*$B$5)) | G25: =IF(OR(F25="",Inputs!$B$30="",Inputs!$B$30=0),"",F25/(Inputs!$B$30*365*2))
A27: STOP RULE 3 — does the answer flip across track-condition scenarios?
A28: Compare the breakeven range above against divertible tonnage on 'Compare'. If the project clears under light rehabilitation and fails under substantial reconstruction, the correct output is INDETERMINATE pending field reconnaissance — not a base case with a verdict attached. Report the scenario at which it flips: that is the single most decision-relevant number in the study.

Sheet Commodity
A1: Commodity segregation and mode-diversion assumptions
A2: The decisive analytical step. Diversion rates are ASSUMPTIONS and the answer is highly sensitive to them — each needs its own cited source before use.
A4: Commodity class | B4: Rail-divertible? | C4: Corridor tonnage (t/yr) | D4: Diversion rate | E4: Divertible tonnage (t/yr) | F4: Source for diversion rate
A5: Cement | B5: yes | E5: =IF(OR(C5="",D5=""),"",C5*D5)
A6: Aggregate | B6: yes | E6: =IF(OR(C6="",D6=""),"",C6*D6)
A7: Fertilizer | B7: yes | E7: =IF(OR(C7="",D7=""),"",C7*D7)
A8: Grain | B8: yes | E8: =IF(OR(C8="",D8=""),"",C8*D8)
A9: Fuel | B9: yes | E9: =IF(OR(C9="",D9=""),"",C9*D9)
A10: Steel | B10: yes | E10: =IF(OR(C10="",D10=""),"",C10*D10)
A11: Containerised manufactured | B11: yes | E11: =IF(OR(C11="",D11=""),"",C11*D11)
A12: Refrigerated | B12: low | E12: =IF(OR(C12="",D12=""),"",C12*D12)
A13: Time-sensitive | B13: low | E13: =IF(OR(C13="",D13=""),"",C13*D13)
A14: High-value low-density agricultural | B14: low | E14: =IF(OR(C14="",D14=""),"",C14*D14)
A15: TOTAL divertible | E15: =IF(COUNT(E5:E14)=0,"",SUM(E5:E14))
A17: Low-diversion classes (mezcal, coffee, avocado, mango, figs) are a large share of Oaxaca's tradeable output and are exactly the goods least likely to move by rail. Segregating them is what prevents a headline tonnage figure from overstating the case.
A18: Aforo data classifies by axle configuration only — there is NO commodity field. Commodity mix must come from production and trade data (SIAP, INEGI Censos Económicos), not from truck counts.

Sheet Supportable
A1: Maximum supportable capital — the screen inverted
A2: A planning-level capital cost for this alignment could not be sourced. So instead: given what the corridor demonstrably moves and what Mexican railways demonstrably earn per ton-km, how much capital could the line support? Needs no capital estimate.
A4: CORRIDOR TONNAGE FROM OBSERVED TRAFFIC
A5: Articulated veh/day, both directions | B5: =Inputs!B32 | C5: veh/day | D5: sct-2025-datosviales-oaxaca (SR-2 bound)
A6: Loaded share | B6: =IF(Inputs!B31="","",1-Inputs!B31) | C6: fraction | D6: [ASSUMPTION] 30–50% empty
A7: Payload per loaded truck | B7: =Inputs!B30 | C7: tonnes | D7: [ASSUMPTION] 25–30 t
A8: Corridor tonnage | B8: =IF(OR(B5="",B6="",B7=""),"",B5*B6*B7*365) | C8: tonnes / yr | D8: derived
A10: MAXIMUM SUPPORTABLE CAPITAL (MXN million per route-km)
A11: Rows = share of corridor freight won by rail [ASSUMPTION]. Columns = cost of capital, 30-year life.
A12: Diversion | B12: Tonnage (t/yr) | C12: Annual surplus (MXN m) | D12: @5% MXN m/km | E12: @6% MXN m/km | F12: @8% MXN m/km
A13: 1 | B13: =IF($B$8="","",$B$8*A13) | C13: =IF(OR(B13="",Inputs!$B$24="",Inputs!$B$5=""),"",B13*Inputs!$B$5*Inputs!$B$24/1000000) | D13: =IF(OR($C13="",Inputs!$B$16="",Inputs!$B$15="",Inputs!$B$5=""),"",$C13*((1-(1+Inputs!$B$16)^-Inputs!$B$15)/Inputs!$B$16)/Inputs!$B$5) | E13: =IF(OR($C13="",Inputs!$B$17="",Inputs!$B$15="",Inputs!$B$5=""),"",$C13*((1-(1+Inputs!$B$17)^-Inputs!$B$15)/Inputs!$B$17)/Inputs!$B$5) | F13: =IF(OR($C13="",Inputs!$B$18="",Inputs!$B$15="",Inputs!$B$5=""),"",$C13*((1-(1+Inputs!$B$18)^-Inputs!$B$15)/Inputs!$B$18)/Inputs!$B$5)
A14: 0.5 | B14: =IF($B$8="","",$B$8*A14) | C14: =IF(OR(B14="",Inputs!$B$24="",Inputs!$B$5=""),"",B14*Inputs!$B$5*Inputs!$B$24/1000000) | D14: =IF(OR($C14="",Inputs!$B$16="",Inputs!$B$15="",Inputs!$B$5=""),"",$C14*((1-(1+Inputs!$B$16)^-Inputs!$B$15)/Inputs!$B$16)/Inputs!$B$5) | E14: =IF(OR($C14="",Inputs!$B$17="",Inputs!$B$15="",Inputs!$B$5=""),"",$C14*((1-(1+Inputs!$B$17)^-Inputs!$B$15)/Inputs!$B$17)/Inputs!$B$5) | F14: =IF(OR($C14="",Inputs!$B$18="",Inputs!$B$15="",Inputs!$B$5=""),"",$C14*((1-(1+Inputs!$B$18)^-Inputs!$B$15)/Inputs!$B$18)/Inputs!$B$5)
A15: 0.3 | B15: =IF($B$8="","",$B$8*A15) | C15: =IF(OR(B15="",Inputs!$B$24="",Inputs!$B$5=""),"",B15*Inputs!$B$5*Inputs!$B$24/1000000) | D15: =IF(OR($C15="",Inputs!$B$16="",Inputs!$B$15="",Inputs!$B$5=""),"",$C15*((1-(1+Inputs!$B$16)^-Inputs!$B$15)/Inputs!$B$16)/Inputs!$B$5) | E15: =IF(OR($C15="",Inputs!$B$17="",Inputs!$B$15="",Inputs!$B$5=""),"",$C15*((1-(1+Inputs!$B$17)^-Inputs!$B$15)/Inputs!$B$17)/Inputs!$B$5) | F15: =IF(OR($C15="",Inputs!$B$18="",Inputs!$B$15="",Inputs!$B$5=""),"",$C15*((1-(1+Inputs!$B$18)^-Inputs!$B$15)/Inputs!$B$18)/Inputs!$B$5)
A16: 0.15 | B16: =IF($B$8="","",$B$8*A16) | C16: =IF(OR(B16="",Inputs!$B$24="",Inputs!$B$5=""),"",B16*Inputs!$B$5*Inputs!$B$24/1000000) | D16: =IF(OR($C16="",Inputs!$B$16="",Inputs!$B$15="",Inputs!$B$5=""),"",$C16*((1-(1+Inputs!$B$16)^-Inputs!$B$15)/Inputs!$B$16)/Inputs!$B$5) | E16: =IF(OR($C16="",Inputs!$B$17="",Inputs!$B$15="",Inputs!$B$5=""),"",$C16*((1-(1+Inputs!$B$17)^-Inputs!$B$15)/Inputs!$B$17)/Inputs!$B$5) | F16: =IF(OR($C16="",Inputs!$B$18="",Inputs!$B$15="",Inputs!$B$5=""),"",$C16*((1-(1+Inputs!$B$18)^-Inputs!$B$15)/Inputs!$B$18)/Inputs!$B$5)
A19: BENCHMARKS
A20: UNESCAP light rehabilitation | B20: =IF(Inputs!B26="","",0.5*Inputs!B26) | C20: MXN million / km | D20: < USD 500,000/route-km, converted at Inputs!B26 — state the rate and its date
A21: Línea Z Mexican precedent | B21: 60 | C21: MXN million / km | D21: ~18,000 MXN million / ~300 km [PRESS — UNVERIFIED, must not carry a conclusion]
A23: VERDICT TEST | B23: =IF(OR(D13="",B21=""),"pending inputs",IF(F13<B21,"FAILS — even 100% capture at the highest cost of capital cannot support the Mexican precedent unit cost","review"))

Sheet Compare
A1: Compare — divertible tonnage against breakeven
A2: Filled once both sides exist. Ranges, not point estimates.
A4: Quantity | B4: Value | C4: Unit | D4: Source
A5: Divertible tonnage (bottom-up, commodity) | B5: =Commodity!E15 | C5: t / yr | D5: Commodity sheet
A6: Breakeven tonnage — most favourable case | B6: =IF(COUNT(Breakeven!F8:F25)=0,"",MIN(Breakeven!F8:F25)) | C6: t / yr | D6: Breakeven sheet
A7: Breakeven tonnage — least favourable case | B7: =IF(COUNT(Breakeven!F8:F25)=0,"",MAX(Breakeven!F8:F25)) | C7: t / yr | D7: Breakeven sheet
A8: Ratio: divertible / breakeven (favourable) | B8: =IF(OR(B5="",B6="",B6=0),"",B5/B6) | C8: x
A9: Ratio: divertible / breakeven (unfavourable) | B9: =IF(OR(B5="",B7="",B7=0),"",B5/B7) | C9: x
A11: VERDICT GATE
A12: Stop Rule 3 test | B12: =IF(OR(B8="",B9=""),"pending inputs",IF(AND(B8>1,B9<1),"INDETERMINATE — scenarios straddle breakeven; field reconnaissance required",IF(B8<1,"FAILS under every capital scenario",IF(B9>1,"CLEARS under every capital scenario","review"))))
A14: A straddle is a real result, not a failure to decide. Per the brief, do not select a base case and present a conclusion — report the scenario at which the answer flips.
